v2_with_change_return/vending_machine_with_return.v
module vending_machine_with_return(
    input clk,
    input rst,
    input coin5,
    input coin10,
    output reg return,
    output reg dispance
);

reg [1:0]state , next_state;

parameter s0 = 2'b00,
          s1 = 2'b01,
          s2 = 2'b10,
          s3 = 2'b11;
always @(posedge clk or posedge rst) begin
  
  if(rst)
  state <= 2'b00;

  else 
  state <= next_state;

end

always @(*) begin
  
  case(state)
  s0 : if(coin5)
       next_state = s1;
    
       else if(coin10)
       next_state = s2;

       else 
       next_state = s0;


  s1 : if(coin5)
       next_state = s2;
    
       else if(coin10)
       next_state = s3;

       else
       next_state = s1;

  s2: next_state = s0;

  s3: next_state = s0;

   default : next_state = s0;
  endcase
end

always @(*)begin
dispance =0;
return =0;

  case(state)
     s2 : dispance =1;

     s3 : begin
       dispance =1;
       return =1;
     end
   endcase
end
endmodule

v2_with_change_return/tb_vending_machine_with_return.v
module tb_vending_machine_with_return;
reg clk, rst, coin5, coin10;
wire return, dispance;

vending_machine_with_return uut(
    .clk(clk),
    .rst(rst),
    .coin5(coin5),
    .coin10(coin10),
    .return(return),
    .dispance(dispance)
);

always #5 clk = ~clk;

initial begin
$dumpfile("tb_vending_machine_with_return.vcd");
$dumpvars(0, tb_vending_machine_with_return);

  
  clk =0;
  rst =1;
  coin5=0;
  coin10=0;

  #10 rst =0;

  #10 coin5 =1;
  #10 coin5 =0;

  #10 coin5 =1;
  #10 coin5 =0;

  #10 coin10 =1;
  #10 coin10 =0;

  #10 coin5 =1;
  #10 coin5 =0;

  #10 coin10 =1;
  #10 coin10 =0;

  #20 $finish;

end
endmodule

v2_with_change_return/tb_vending_machine_with_return.vcd
$date
	Sat Feb 21 19:21:58 2026
$end
$version
	Icarus Verilog
$end
$timescale
	1s
$end
$scope module tb_vending_machine_with_return $end
$var wire 1 ! return $end
$var wire 1 " dispance $end
$var reg 1 # clk $end
$var reg 1 $ coin10 $end
$var reg 1 % coin5 $end
$var reg 1 & rst $end
$scope module uut $end
$var wire 1 # clk $end
$var wire 1 $ coin10 $end
$var wire 1 % coin5 $end
$var wire 1 & rst $end
$var parameter 2 ' s0 $end
$var parameter 2 ( s1 $end
$var parameter 2 ) s2 $end
$var parameter 2 * s3 $end
$var reg 1 " dispance $end
$var reg 2 + next_state [1:0] $end
$var reg 1 ! return $end
$var reg 2 , state [1:0] $end
$upscope $end
$upscope $end
$enddefinitions $end
$comment Show the parameter values. $end
$dumpall
b11 *
b10 )
b1 (
b0 '
$end
#0
$dumpvars
b0 ,
b0 +
1&
0%
0$
0#
0"
0!
$end
#5
1#
#10
0#
0&
#15
1#
#20
b1 +
0#
1%
#25
b10 +
b1 ,
1#
#30
b1 +
0#
0%
#35
1#
#40
b10 +
0#
1%
#45
1"
b0 +
b10 ,
1#
#50
0#
0%
#55
0"
b0 ,
1#
#60
b10 +
0#
1$
#65
1"
b0 +
b10 ,
1#
#70
0#
0$
#75
0"
b0 ,
1#
#80
b1 +
0#
1%
#85
b10 +
b1 ,
1#
#90
b1 +
0#
0%
#95
1#
#100
b11 +
0#
1$
#105
1!
1"
b0 +
b11 ,
1#
#110
0#
0$
#115
0!
0"
b0 ,
1#
